[
  {
    "id": 10001,
    "message": "Applied to your task",
    "type": "Application",
    "targetEntityId": 10011,
    "userId": 10001,
    "notifierId": 10006,
    "isRead": false
  },
  {
    "id": 10002,
    "message": "Applied to your task",
    "type": "Application",
    "targetEntityId": 10001,
    "userId": 10001,
    "notifierId": 10006,
    "isRead": false
  },
  {
    "id": 10003,
    "message": "Applied to your task",
    "type": "Application",
    "targetEntityId": 10011,
    "userId": 10001,
    "notifierId": 10009,
    "isRead": false
  },
  {
    "id": 10004,
    "message": "Applied to your task",
    "type": "Application",
    "targetEntityId": 10001,
    "userId": 10001,
    "notifierId": 10009,
    "isRead": false
  },
  {
    "id": 10005,
    "message": "Sent You a message",
    "type": "Message",
    "targetEntityId": 10001,
    "userId": 10001,
    "notifierId": 10009,
    "isRead": false
  },
  {
    "id": 10006,
    "message": "Sent You a message",
    "type": "Message",
    "targetEntityId": 10001,
    "userId": 10001,
    "notifierId": 10006,
    "isRead": false
  }
]
